{
  "attributes": {
    "kibanaSavedObjectMeta": {
      "searchSourceJSON": "{\"query\":{\"query\":\"\",\"language\":\"kuery\"},\"filter\":[],\"index\":\"batch-events\"}"
    },
    "title": "All Batch Events",
    "sort": [
      [
        "@timestamp",
        "desc"
      ]
    ],
    "columns": [
      "@timestamp",
      "event_kind",
      "class",
      "matched",
      "event_uid",
      "start_event_uid"
    ],
    "description": "A list of the start, end, and point batch events.",
    "hideChart": false,
    "isTextBasedQuery": false,
    "usesAdHocDataView": false,
    "timeRestore": false,
    "rowHeight": 3,
    "rowsPerPage": 100
  }
}