{
  "annotations": {
    "list": [
      {
        "builtIn": 1,
        "datasource": "-- Grafana --",
        "enable": true,
        "hide": true,
        "iconColor": "rgba(0, 211, 255, 1)",
        "name": "Annotations & Alerts",
        "type": "dashboard"
      }
    ]
  },
  "editable": true,
  "gnetId": null,
  "graphTooltip": 0,
  "id": null,
  "links": [
    {
      "asDropdown": false,
      "icon": "external link",
      "includeVars": true,
      "keepTime": true,
      "tags": [],
      "targetBlank": true,
      "title": "View Detailed Logs",
      "tooltip": "Click to view detailed application logs",
      "type": "link",
      "url": "/d/spark-logs-viewer"
    }
  ],
  "panels": [
    {
      "datasource": {
        "type": "elasticsearch",
        "uid": "spark-elasticsearch"
      },
      "fieldConfig": {
        "defaults": {
          "color": {
            "mode": "palette-classic"
          },
          "custom": {
            "axisBorderShow": false,
            "axisCenteredZero": false,
            "axisColorMode": "text",
            "axisLabel": "Jobs",
            "axisPlacement": "left",
            "barAlignment": 0,
            "barWidthFactor": 0.6,
            "drawStyle": "bars",
            "fillOpacity": 100,
            "gradientMode": "none",
            "hideFrom": {
              "legend": false,
              "tooltip": false,
              "viz": false
            },
            "insertNulls": false,
            "lineInterpolation": "linear",
            "lineWidth": 1,
            "pointSize": 1,
            "scaleDistribution": {
              "type": "linear"
            },
            "showPoints": "never",
            "spanNulls": false,
            "stacking": {
              "group": "A",
              "mode": "normal"
            },
            "thresholdsStyle": {
              "mode": "off"
            },
            "axisWidth": 40
          },
          "mappings": [],
          "thresholds": {
            "mode": "absolute",
            "steps": [
              {
                "color": "green",
                "value": null
              }
            ]
          },
          "unit": "none"
        },
        "overrides": []
      },
      "gridPos": {
        "h": 8,
        "w": 12,
        "x": 0,
        "y": 0
      },
      "id": 101,
      "options": {
        "legend": {
          "displayMode": "list",
          "placement": "bottom",
          "showLegend": true,
          "calcs": []
        },
        "tooltip": {
          "mode": "multi",
          "sort": "none"
        }
      },
      "targets": [
        {
          "bucketAggs": [
            {
              "id": "3",
              "type": "terms",
              "field": "operation.type",
              "settings": {
                "min_doc_count": "1",
                "order": "desc",
                "orderBy": "_count",
                "size": "32"
              }
            },
            {
              "id": "2",
              "type": "date_histogram",
              "field": "@timestamp",
              "settings": {
                "interval": "$__interval",
                "min_doc_count": "0"
              }
            }
          ],
          "datasource": {
            "type": "elasticsearch",
            "uid": "spark-elasticsearch"
          },
          "metrics": [
            {
              "id": "1",
              "type": "count"
            }
          ],
          "query": "_index:app-events-* AND event.type:\"start\" AND event.state:\"open\"",
          "refId": "A",
          "timeField": "@timestamp",
          "alias": ""
        }
      ],
      "title": "Active Application Jobs",
      "description": "Open START events from app-events-* (direct query). The application-events-metrics-ds watcher is not available under Elasticsearch Basic license.",
      "type": "timeseries"
    },
    {
      "datasource": {
        "type": "elasticsearch",
        "uid": "spark-elasticsearch"
      },
      "fieldConfig": {
        "defaults": {
          "custom": {
            "drawStyle": "bars",
            "barAlignment": 0,
            "barWidthFactor": 0.6,
            "fillOpacity": 100,
            "stacking": {
              "group": "A",
              "mode": "normal"
            },
            "axisLabel": "Count",
            "axisPlacement": "left",
            "axisWidth": 40,
            "axisBorderShow": false,
            "axisColorMode": "text",
            "axisCenteredZero": false
          },
          "unit": "none",
          "color": {
            "mode": "palette-classic"
          }
        }
      },
      "gridPos": {
        "h": 8,
        "w": 12,
        "x": 0,
        "y": 8
      },
      "id": 100,
      "options": {
        "legend": {
          "displayMode": "list",
          "placement": "bottom",
          "showLegend": true,
          "calcs": []
        },
        "tooltip": {
          "mode": "multi",
          "sort": "none"
        }
      },
      "pluginVersion": "11.3.0",
      "targets": [
        {
          "alias": "{{term log.level}}",
          "bucketAggs": [
            {
              "field": "log.level",
              "id": "3",
              "settings": {
                "min_doc_count": "1",
                "order": "desc",
                "orderBy": "_term",
                "size": "16"
              },
              "type": "terms"
            },
            {
              "field": "@timestamp",
              "id": "2",
              "settings": {
                "interval": "$__interval",
                "min_doc_count": "0",
                "trimEdges": "0"
              },
              "type": "date_histogram"
            }
          ],
          "datasource": {
            "type": "elasticsearch",
            "uid": "spark-elasticsearch"
          },
          "metrics": [
            {
              "id": "1",
              "type": "count"
            }
          ],
          "query": "_index:logs-spark-default*",
          "refId": "A",
          "timeField": "@timestamp"
        }
      ],
      "title": "Spark Application Log Counts",
      "type": "timeseries",
      "description": "Aggregated count of Spark application log entries by log level. Click on data points to view detailed logs."
    },
    {
      "datasource": {
        "type": "elasticsearch",
        "uid": "spark-elasticsearch"
      },
      "fieldConfig": {
        "defaults": {
          "color": {
            "mode": "palette-classic"
          },
          "custom": {
            "axisBorderShow": false,
            "axisCenteredZero": false,
            "axisColorMode": "text",
            "axisLabel": "CPU Utilization %",
            "axisPlacement": "left",
            "barAlignment": 0,
            "drawStyle": "line",
            "fillOpacity": 20,
            "gradientMode": "none",
            "hideFrom": {
              "tooltip": false,
              "viz": false,
              "legend": false
            },
            "lineInterpolation": "linear",
            "lineWidth": 2,
            "pointSize": 5,
            "scaleDistribution": {
              "type": "linear",
              "min": 0,
              "max": 1.0
            },
            "showPoints": "never",
            "spanNulls": true,
            "axisWidth": 40
          },
          "mappings": [],
          "thresholds": {
            "mode": "absolute",
            "steps": [
              {
                "color": "green",
                "value": null
              },
              {
                "color": "yellow",
                "value": 0.6
              },
              {
                "color": "red",
                "value": 0.8
              }
            ]
          },
          "unit": "percentunit"
        },
        "overrides": []
      },
      "gridPos": {
        "h": 8,
        "w": 12,
        "x": 12,
        "y": 8
      },
      "id": 2,
      "options": {
        "legend": {
          "displayMode": "list",
          "placement": "bottom",
          "showLegend": true,
          "calcs": []
        },
        "tooltip": {
          "mode": "single"
        }
      },
      "pluginVersion": "11.3.0",
      "targets": [
        {
          "bucketAggs": [
            {
              "field": "@timestamp",
              "id": "2",
              "settings": {
                "interval": "$__interval"
              },
              "type": "date_histogram"
            }
          ],
          "datasource": {
            "type": "elasticsearch",
            "uid": "spark-elasticsearch"
          },
          "metrics": [
            {
              "field": "system.cpu.total.norm.pct",
              "id": "1",
              "type": "avg"
            }
          ],
          "query": "_index:metrics-system.cpu-default*",
          "refId": "A",
          "timeField": "@timestamp",
          "alias": "Average CPU Usage"
        }
      ],
      "title": "Average System CPU Utilization %",
      "type": "timeseries"
    },
    {
      "datasource": {
        "type": "elasticsearch",
        "uid": "spark-elasticsearch"
      },
      "fieldConfig": {
        "defaults": {
          "color": {
            "mode": "palette-classic"
          },
          "custom": {
            "axisBorderShow": false,
            "axisCenteredZero": false,
            "axisColorMode": "text",
            "axisLabel": "Memory Utilization %",
            "axisPlacement": "left",
            "barAlignment": 0,
            "drawStyle": "line",
            "fillOpacity": 20,
            "gradientMode": "none",
            "hideFrom": {
              "tooltip": false,
              "viz": false,
              "legend": false
            },
            "lineInterpolation": "linear",
            "lineWidth": 2,
            "pointSize": 5,
            "scaleDistribution": {
              "type": "linear"
            },
            "showPoints": "never",
            "spanNulls": true,
            "axisWidth": 40
          },
          "mappings": [],
          "thresholds": {
            "mode": "absolute",
            "steps": [
              {
                "color": "green",
                "value": null
              },
              {
                "color": "yellow",
                "value": 60
              },
              {
                "color": "red",
                "value": 80
              }
            ]
          },
          "unit": "percentunit"
        },
        "overrides": []
      },
      "gridPos": {
        "h": 8,
        "w": 12,
        "x": 0,
        "y": 16
      },
      "id": 3,
      "options": {
        "legend": {
          "displayMode": "list",
          "placement": "bottom",
          "showLegend": true,
          "calcs": []
        },
        "tooltip": {
          "mode": "single"
        }
      },
      "pluginVersion": "11.3.0",
      "targets": [
        {
          "bucketAggs": [
            {
              "field": "@timestamp",
              "id": "2",
              "settings": {
                "interval": "$__interval"
              },
              "type": "date_histogram"
            }
          ],
          "datasource": {
            "type": "elasticsearch",
            "uid": "spark-elasticsearch"
          },
          "metrics": [
            {
              "field": "system.memory.used.pct",
              "id": "1",
              "type": "avg"
            }
          ],
          "query": "_index:metrics-system.memory-default*",
          "refId": "A",
          "timeField": "@timestamp",
          "alias": "Average Memory Usage"
        }
      ],
      "title": "Average System Memory Utilization %",
      "type": "timeseries"
    },
    {
      "datasource": {
        "type": "elasticsearch",
        "uid": "spark-elasticsearch"
      },
      "fieldConfig": {
        "defaults": {
          "color": {
            "mode": "palette-classic"
          },
          "custom": {
            "lineWidth": 2,
            "fillOpacity": 10,
            "spanNulls": false,
            "stacking": {
              "mode": "normal",
              "group": "A"
            },
            "axisLabel": "Bytes/sec",
            "axisPlacement": "left",
            "axisWidth": 40,
            "axisBorderShow": false,
            "axisColorMode": "text",
            "axisCenteredZero": false
          },
          "mappings": [],
          "nullValueMode": "null",
          "unit": "short"
        },
        "overrides": []
      },
      "gridPos": {
        "h": 8,
        "w": 12,
        "x": 0,
        "y": 24
      },
      "id": 10,
      "options": {
        "legend": {
          "displayMode": "list",
          "placement": "bottom",
          "showLegend": true,
          "calcs": []
        },
        "tooltip": {
          "mode": "multi"
        },
        "maxDataPoints": 3000
      },
      "pluginVersion": "11.3.0",
      "targets": [
        {
          "datasource": {
            "type": "elasticsearch",
            "uid": "spark-elasticsearch"
          },
          "query": "_index:metrics-system.network-default* AND NOT system.network.name:lo AND NOT system.network.name:veth* AND NOT system.network.name:docker* AND NOT system.network.name:br-* AND NOT system.network.name:virbr* AND _exists_:system.network.in.bytes_rate",
          "alias": "Total In",
          "metrics": [
            {
              "id": "1",
              "type": "sum",
              "field": "system.network.in.bytes_rate",
              "hide": true
            },
            {
              "id": "2",
              "type": "bucket_script",
              "pipelineAgg": "1",
              "settings": {
                "script": "params._value != null && params._value >= 0 ? params._value * -1 : null"
              },
              "pipelineVariables": [
                {
                  "name": "_value",
                  "pipelineAgg": "1"
                }
              ]
            }
          ],
          "bucketAggs": [
            {
              "id": "3",
              "type": "date_histogram",
              "field": "@timestamp",
              "settings": {
                "interval": "$__interval",
                "min_doc_count": 0
              }
            }
          ],
          "refId": "A",
          "timeField": "@timestamp"
        },
        {
          "datasource": {
            "type": "elasticsearch",
            "uid": "spark-elasticsearch"
          },
          "query": "_index:metrics-system.network-default* AND NOT system.network.name:lo AND NOT system.network.name:veth* AND NOT system.network.name:docker* AND NOT system.network.name:br-* AND NOT system.network.name:virbr* AND _exists_:system.network.out.bytes_rate",
          "alias": "Total Out",
          "metrics": [
            {
              "id": "1",
              "type": "sum",
              "field": "system.network.out.bytes_rate",
              "hide": true
            },
            {
              "id": "2",
              "type": "bucket_script",
              "pipelineAgg": "1",
              "settings": {
                "script": "params._value != null && params._value >= 0 ? params._value : null"
              },
              "pipelineVariables": [
                {
                  "name": "_value",
                  "pipelineAgg": "1"
                }
              ]
            }
          ],
          "bucketAggs": [
            {
              "id": "3",
              "type": "date_histogram",
              "field": "@timestamp",
              "settings": {
                "interval": "$__interval",
                "min_doc_count": 0
              }
            }
          ],
          "refId": "B",
          "timeField": "@timestamp"
        }
      ],
      "title": "Total Network Byte Rate (In/Out)",
      "type": "timeseries",
      "description": "Aggregated network I/O rates using precomputed rates from Logstash aggregate filter"
    },
    {
      "datasource": {
        "type": "elasticsearch",
        "uid": "spark-elasticsearch"
      },
      "fieldConfig": {
        "defaults": {
          "color": {
            "mode": "palette-classic"
          },
          "custom": {
            "lineWidth": 2,
            "fillOpacity": 10,
            "spanNulls": false,
            "stacking": {
              "mode": "normal",
              "group": "A"
            },
            "axisLabel": "Bytes/sec",
            "axisPlacement": "left",
            "axisWidth": 40,
            "axisBorderShow": false,
            "axisColorMode": "text",
            "axisCenteredZero": false
          },
          "mappings": [],
          "nullValueMode": "null",
          "unit": "short"
        },
        "overrides": []
      },
      "gridPos": {
        "h": 8,
        "w": 12,
        "x": 12,
        "y": 24
      },
      "id": 11,
      "options": {
        "legend": {
          "displayMode": "list",
          "placement": "bottom",
          "showLegend": true,
          "calcs": []
        },
        "tooltip": {
          "mode": "multi"
        },
        "maxDataPoints": 3000
      },
      "pluginVersion": "11.3.0",
      "targets": [
        {
          "datasource": {
            "type": "elasticsearch",
            "uid": "spark-elasticsearch"
          },
          "query": "_index:metrics-system.diskio-default* AND system.diskio.name:(nvme* OR sd* OR vd*) AND _exists_:system.diskio.read.bytes_rate",
          "alias": "Total Read",
          "metrics": [
            {
              "id": "1",
              "type": "sum",
              "field": "system.diskio.read.bytes_rate",
              "hide": true
            },
            {
              "id": "2",
              "type": "bucket_script",
              "pipelineAgg": "1",
              "settings": {
                "script": "params._value != null && params._value >= 0 ? params._value * -1 : null"
              },
              "pipelineVariables": [
                {
                  "name": "_value",
                  "pipelineAgg": "1"
                }
              ]
            }
          ],
          "bucketAggs": [
            {
              "id": "3",
              "type": "date_histogram",
              "field": "@timestamp",
              "settings": {
                "interval": "$__interval",
                "min_doc_count": 0
              }
            }
          ],
          "refId": "A",
          "timeField": "@timestamp"
        },
        {
          "datasource": {
            "type": "elasticsearch",
            "uid": "spark-elasticsearch"
          },
          "query": "_index:metrics-system.diskio-default* AND system.diskio.name:(nvme* OR sd* OR vd*) AND _exists_:system.diskio.write.bytes_rate",
          "alias": "Total Write",
          "metrics": [
            {
              "id": "1",
              "type": "sum",
              "field": "system.diskio.write.bytes_rate",
              "hide": true
            },
            {
              "id": "2",
              "type": "bucket_script",
              "pipelineAgg": "1",
              "settings": {
                "script": "params._value != null && params._value >= 0 ? params._value : null"
              },
              "pipelineVariables": [
                {
                  "name": "_value",
                  "pipelineAgg": "1"
                }
              ]
            }
          ],
          "bucketAggs": [
            {
              "id": "3",
              "type": "date_histogram",
              "field": "@timestamp",
              "settings": {
                "interval": "$__interval",
                "min_doc_count": 0
              }
            }
          ],
          "refId": "B",
          "timeField": "@timestamp"
        }
      ],
      "title": "Total Disk I/O Rate (Read/Write)",
      "type": "timeseries",
      "description": "Aggregated disk I/O rates using precomputed rates from Logstash aggregate filter"
    },
    {
      "datasource": {
        "type": "elasticsearch",
        "uid": "spark-elasticsearch"
      },
      "fieldConfig": {
        "defaults": {
          "color": {
            "mode": "palette-classic"
          },
          "custom": {
            "axisLabel": "Load",
            "axisPlacement": "left",
            "barAlignment": 0,
            "drawStyle": "line",
            "fillOpacity": 20,
            "gradientMode": "none",
            "hideFrom": {
              "tooltip": false,
              "viz": false,
              "legend": false
            },
            "lineInterpolation": "linear",
            "lineWidth": 2,
            "pointSize": 5,
            "scaleDistribution": {
              "type": "linear"
            },
            "showPoints": "never",
            "spanNulls": false,
            "axisWidth": 40,
            "axisBorderShow": false,
            "axisColorMode": "text",
            "axisCenteredZero": false
          },
          "mappings": [],
          "nullValueMode": "null",
          "thresholds": {
            "mode": "absolute",
            "steps": [
              {
                "color": "green",
                "value": null
              }
            ]
          },
          "unit": "none"
        },
        "overrides": []
      },
      "gridPos": {
        "h": 8,
        "w": 12,
        "x": 0,
        "y": 32
      },
      "id": 7,
      "options": {
        "legend": {
          "displayMode": "list",
          "placement": "bottom",
          "showLegend": true,
          "calcs": []
        },
        "tooltip": {
          "mode": "multi"
        }
      },
      "pluginVersion": "11.3.0",
      "targets": [
        {
          "refId": "A",
          "datasource": {
            "type": "elasticsearch",
            "uid": "spark-elasticsearch"
          },
          "query": "_index:metrics-system.load-default*",
          "metrics": [
            {
              "id": "1",
              "type": "sum",
              "field": "system.load.1"
            }
          ],
          "bucketAggs": [
            {
              "id": "2",
              "type": "date_histogram",
              "field": "@timestamp",
              "settings": {
                "interval": "$__interval"
              }
            }
          ],
          "alias": "Total Load (1-minute)",
          "timeField": "@timestamp"
        }
      ],
      "title": "Total System Load Average (1-minute)",
      "type": "timeseries",
      "description": "Total 1-minute load average across all hosts. For Default granularity. For 5m/15m/60m granularities, this represents the smoothed load over those intervals."
    },
    {
      "datasource": {
        "type": "elasticsearch",
        "uid": "spark-elasticsearch"
      },
      "fieldConfig": {
        "defaults": {
          "color": {
            "mode": "palette-classic"
          },
          "custom": {
            "axisLabel": "Faults/sec",
            "axisPlacement": "left",
            "barAlignment": 0,
            "drawStyle": "line",
            "fillOpacity": 20,
            "gradientMode": "none",
            "hideFrom": {
              "tooltip": false,
              "viz": false,
              "legend": false
            },
            "lineInterpolation": "linear",
            "lineWidth": 2,
            "pointSize": 5,
            "scaleDistribution": {
              "type": "linear"
            },
            "showPoints": "never",
            "spanNulls": false,
            "axisWidth": 40,
            "axisBorderShow": false,
            "axisColorMode": "text",
            "axisCenteredZero": false
          },
          "mappings": [],
          "nullValueMode": "null",
          "thresholds": {
            "mode": "absolute",
            "steps": [
              {
                "color": "green",
                "value": null
              }
            ]
          },
          "unit": "none"
        },
        "overrides": []
      },
      "gridPos": {
        "h": 8,
        "w": 12,
        "x": 12,
        "y": 32
      },
      "id": 6,
      "options": {
        "legend": {
          "displayMode": "list",
          "placement": "bottom",
          "showLegend": true,
          "calcs": []
        },
        "tooltip": {
          "mode": "multi"
        }
      },
      "pluginVersion": "11.3.0",
      "targets": [
        {
          "bucketAggs": [
            {
              "field": "@timestamp",
              "id": "2",
              "settings": {
                "interval": "$__interval"
              },
              "type": "date_histogram"
            }
          ],
          "datasource": {
            "type": "elasticsearch",
            "uid": "spark-elasticsearch"
          },
          "metrics": [
            {
              "field": "system.memory.page_stats.pgfault.rate",
              "id": "1",
              "type": "sum"
            }
          ],
          "query": "_index:metrics-system.memory-default*",
          "refId": "A",
          "timeField": "@timestamp",
          "alias": "Total Page Faults"
        },
        {
          "bucketAggs": [
            {
              "field": "@timestamp",
              "id": "2",
              "settings": {
                "interval": "$__interval"
              },
              "type": "date_histogram"
            }
          ],
          "datasource": {
            "type": "elasticsearch",
            "uid": "spark-elasticsearch"
          },
          "metrics": [
            {
              "field": "system.memory.page_stats.pgmajfault.rate",
              "id": "1",
              "type": "sum"
            }
          ],
          "query": "_index:metrics-system.memory-default*",
          "refId": "B",
          "timeField": "@timestamp",
          "alias": "Total Major Faults"
        }
      ],
      "title": "Total Page Fault Rate",
      "type": "timeseries"
    },
    {
      "datasource": {
        "type": "elasticsearch",
        "uid": "spark-elasticsearch"
      },
      "fieldConfig": {
        "defaults": {
          "color": {
            "mode": "palette-classic"
          },
          "custom": {
            "axisBorderShow": false,
            "axisCenteredZero": false,
            "axisColorMode": "text",
            "axisLabel": "Milliseconds",
            "axisPlacement": "left",
            "fillOpacity": 20,
            "gradientMode": "none",
            "hideFrom": {
              "tooltip": false,
              "viz": false,
              "legend": false
            },
            "lineWidth": 2,
            "scaleDistribution": {
              "type": "linear"
            },
            "thresholdsStyle": {
              "mode": "off"
            },
            "axisWidth": 40
          },
          "links": [],
          "mappings": [],
          "thresholds": {
            "mode": "absolute",
            "steps": [
              {
                "color": "green",
                "value": null
              }
            ]
          },
          "unit": "none"
        },
        "overrides": []
      },
      "gridPos": {
        "h": 8,
        "w": 12,
        "x": 0,
        "y": 40
      },
      "id": 8,
      "options": {
        "legend": {
          "calcs": [],
          "displayMode": "list",
          "placement": "bottom",
          "showLegend": true
        },
        "tooltip": {
          "mode": "multi",
          "sort": "none"
        }
      },
      "pluginVersion": "11.3.0",
      "targets": [
        {
          "alias": "Total GC Pause Time",
          "bucketAggs": [
            {
              "field": "@timestamp",
              "id": "2",
              "settings": {
                "interval": "$__interval",
                "min_doc_count": "0"
              },
              "type": "date_histogram"
            }
          ],
          "datasource": {
            "type": "elasticsearch",
            "uid": "spark-elasticsearch"
          },
          "metrics": [
            {
              "id": "1",
              "type": "sum",
              "field": "gc.paused.millis"
            }
          ],
          "query": "_index:logs-spark_gc-default*",
          "refId": "A",
          "timeField": "@timestamp"
        }
      ],
      "title": "Total GC Pause Time",
      "type": "timeseries"
    },
    {
      "datasource": {
        "type": "elasticsearch",
        "uid": "spark-elasticsearch"
      },
      "fieldConfig": {
        "defaults": {
          "color": {
            "mode": "palette-classic"
          },
          "custom": {
            "axisBorderShow": false,
            "axisCenteredZero": false,
            "axisColorMode": "text",
            "axisLabel": "Bytes",
            "axisPlacement": "left",
            "fillOpacity": 20,
            "gradientMode": "none",
            "hideFrom": {
              "tooltip": false,
              "viz": false,
              "legend": false
            },
            "lineWidth": 2,
            "scaleDistribution": {
              "type": "linear"
            },
            "thresholdsStyle": {
              "mode": "off"
            },
            "axisWidth": 40
          },
          "mappings": [],
          "thresholds": {
            "mode": "absolute",
            "steps": [
              {
                "color": "green",
                "value": null
              }
            ]
          },
          "unit": "short"
        },
        "overrides": []
      },
      "gridPos": {
        "h": 8,
        "w": 12,
        "x": 12,
        "y": 40
      },
      "id": 9,
      "options": {
        "legend": {
          "calcs": [],
          "displayMode": "list",
          "placement": "bottom",
          "showLegend": true
        },
        "tooltip": {
          "mode": "multi",
          "sort": "none"
        }
      },
      "pluginVersion": "11.3.0",
      "targets": [
        {
          "alias": "Total Heap Reclaimed",
          "bucketAggs": [
            {
              "field": "@timestamp",
              "id": "2",
              "settings": {
                "interval": "$__interval",
                "min_doc_count": "0"
              },
              "type": "date_histogram"
            }
          ],
          "datasource": {
            "type": "elasticsearch",
            "uid": "spark-elasticsearch"
          },
          "metrics": [
            {
              "id": "1",
              "type": "sum",
              "field": "gc.paused.reclaimed"
            }
          ],
          "query": "_index:logs-spark_gc-default*",
          "refId": "A",
          "timeField": "@timestamp"
        }
      ],
      "title": "Total GC Heap Reclaimed",
      "type": "timeseries"
    },
    {
      "datasource": {
        "type": "elasticsearch",
        "uid": "spark-elasticsearch"
      },
      "fieldConfig": {
        "defaults": {
          "color": {
            "mode": "palette-classic"
          },
          "custom": {
            "axisLabel": "%",
            "axisPlacement": "left",
            "axisWidth": 36,
            "barAlignment": 0,
            "drawStyle": "line",
            "fillOpacity": 20,
            "gradientMode": "none",
            "hideFrom": {
              "legend": false,
              "tooltip": false,
              "viz": false
            },
            "lineInterpolation": "linear",
            "lineWidth": 2,
            "pointSize": 4,
            "scaleDistribution": {
              "type": "linear"
            },
            "showPoints": "never",
            "spanNulls": true,
            "axisBorderShow": false,
            "axisColorMode": "text",
            "axisCenteredZero": true
          },
          "decimals": 0,
          "mappings": [],
          "thresholds": {
            "mode": "absolute",
            "steps": [
              {
                "color": "green",
                "value": null
              },
              {
                "color": "red",
                "value": 90
              }
            ]
          },
          "min": -100,
          "max": 100,
          "unit": "none"
        },
        "overrides": []
      },
      "gridPos": {
        "h": 8,
        "w": 12,
        "x": 0,
        "y": 48
      },
      "id": 103,
      "options": {
        "legend": {
          "calcs": [],
          "displayMode": "list",
          "placement": "bottom",
          "showLegend": true
        },
        "tooltip": {
          "mode": "multi"
        }
      },
      "pluginVersion": "11.3.0",
      "targets": [
        {
          "alias": "Average GPU %",
          "bucketAggs": [
            {
              "field": "@timestamp",
              "id": "2",
              "settings": {
                "interval": "$__interval"
              },
              "type": "date_histogram"
            }
          ],
          "datasource": {
            "type": "elasticsearch",
            "uid": "spark-elasticsearch"
          },
          "metrics": [
            {
              "field": "gpu.utilization.core_percent",
              "id": "1",
              "type": "avg"
            }
          ],
          "query": "_index:metrics-gpu-default*",
          "refId": "A",
          "timeField": "@timestamp"
        },
        {
          "alias": "Average VRAM %",
          "bucketAggs": [
            {
              "field": "@timestamp",
              "id": "2",
              "settings": {
                "interval": "$__interval"
              },
              "type": "date_histogram"
            }
          ],
          "datasource": {
            "type": "elasticsearch",
            "uid": "spark-elasticsearch"
          },
          "metrics": [
            {
              "field": "gpu.utilization.memory_percent",
              "id": "1",
              "type": "avg",
              "hide": true
            },
            {
              "id": "2",
              "type": "bucket_script",
              "pipelineAgg": "1",
              "settings": {
                "script": "params._value != null ? params._value * -1 : null"
              },
              "pipelineVariables": [
                {
                  "name": "_value",
                  "pipelineAgg": "1"
                }
              ]
            }
          ],
          "query": "_index:metrics-gpu-default*",
          "refId": "B",
          "timeField": "@timestamp"
        }
      ],
      "title": "GPU Utilization (Envelope Plot)",
      "description": "GPU utilization (positive) and VRAM utilization (negative) across Lab1/Lab2 nodes",
      "type": "timeseries"
    },
    {
      "datasource": {
        "type": "elasticsearch",
        "uid": "spark-elasticsearch"
      },
      "fieldConfig": {
        "defaults": {
          "color": {
            "mode": "palette-classic"
          },
          "custom": {
            "axisLabel": "Temperature (\u00b0C)",
            "axisPlacement": "left",
            "barAlignment": 0,
            "drawStyle": "line",
            "fillOpacity": 20,
            "gradientMode": "none",
            "hideFrom": {
              "legend": false,
              "tooltip": false,
              "viz": false
            },
            "lineInterpolation": "linear",
            "lineWidth": 2,
            "pointSize": 4,
            "scaleDistribution": {
              "type": "linear"
            },
            "showPoints": "never",
            "spanNulls": true,
            "axisWidth": 40,
            "axisBorderShow": false,
            "axisColorMode": "text",
            "axisCenteredZero": false
          },
          "mappings": [],
          "thresholds": {
            "mode": "absolute",
            "steps": [
              {
                "color": "green",
                "value": null
              }
            ]
          },
          "unit": "short"
        },
        "overrides": []
      },
      "gridPos": {
        "h": 8,
        "w": 12,
        "x": 12,
        "y": 48
      },
      "id": 102,
      "options": {
        "legend": {
          "calcs": [],
          "displayMode": "list",
          "placement": "bottom",
          "showLegend": true
        },
        "tooltip": {
          "mode": "multi"
        }
      },
      "pluginVersion": "11.3.0",
      "targets": [
        {
          "alias": "Average Edge Temp (\u00b0C)",
          "bucketAggs": [
            {
              "field": "@timestamp",
              "id": "2",
              "settings": {
                "interval": "$__interval"
              },
              "type": "date_histogram"
            }
          ],
          "datasource": {
            "type": "elasticsearch",
            "uid": "spark-elasticsearch"
          },
          "metrics": [
            {
              "field": "gpu.temperature_c.edge",
              "id": "1",
              "type": "avg"
            }
          ],
          "query": "_index:metrics-gpu-default*",
          "refId": "C",
          "timeField": "@timestamp"
        }
      ],
      "title": "GPU Temperature",
      "description": "Average GPU edge temperature across Lab1/Lab2 nodes",
      "type": "timeseries"
    }
  ],
  "refresh": "30s",
  "schemaVersion": 39,
  "style": "dark",
  "tags": [
    "spark",
    "system",
    "metrics",
    "aggregated"
  ],
  "templating": {
    "list": []
  },
  "time": {
    "from": "now-6h",
    "to": "now"
  },
  "timepicker": {},
  "timezone": "browser",
  "title": "Spark System Metrics",
  "uid": "spark-system-metrics-aggregated",
  "version": 6
}